{
  "_note1": "KEEP THIS FILE! Check it into a version control system (VCS) like git.",
  "_note2": "ObjectBox manages crucial IDs for your object model. See docs for details.",
  "_note3": "If you have VCS merge conflicts, you must resolve them according to ObjectBox docs.",
  "entities": [
    {
      "id": "1:8936841568836638275",
      "lastPropertyId": "8:441039116072698280",
      "name": "Alarm",
      "properties": [
        {
          "id": "1:7110678007342841983",
          "name": "id",
          "type": 6,
          "flags": 1
        },
        {
          "id": "2:2483349958949979828",
          "name": "label",
          "type": 9
        },
        {
          "id": "3:3957034052276043853",
          "name": "time",
          "type": 9
        },
        {
          "id": "4:4401949911595251700",
          "name": "daysShort",
          "type": 30
        },
        {
          "id": "5:4774608712235888362",
          "name": "days",
          "type": 30
        },
        {
          "id": "6:6306094912105859487",
          "name": "repeat",
          "type": 30
        },
        {
          "id": "7:3068556074090132350",
          "name": "missions",
          "type": 30
        },
        {
          "id": "8:441039116072698280",
          "name": "enabled",
          "type": 1
        }
      ],
      "relations": []
    }
  ],
  "lastEntityId": "1:8936841568836638275",
  "lastIndexId": "0:0",
  "lastRelationId": "0:0",
  "lastSequenceId": "0:0",
  "modelVersion": 5,
  "modelVersionParserMinimum": 5,
  "retiredEntityUids": [],
  "retiredIndexUids": [],
  "retiredPropertyUids": [],
  "retiredRelationUids": [],
  "version": 1
}